hca_smart_sync/__init__.py
hca_smart_sync/checksum.py
hca_smart_sync/cli.py
hca_smart_sync/config/__init__.py
hca_smart_sync/config_manager.py
hca_smart_sync/manifest.py
hca_smart_sync/sync_engine.py
hca_smart_sync-0.3.0.dist-info/METADATA
hca_smart_sync-0.3.0.dist-info/WHEEL
hca_smart_sync-0.3.0.dist-info/entry_points.txt
hca_smart_sync-0.3.0.dist-info/licenses/LICENSE
hca_smart_sync-0.3.0.dist-info/RECORD
